ekf_slam/__init__.py
ekf_slam/ekf_slam.py
ekf_slam-0.0.2.dist-info/LICENSE
ekf_slam-0.0.2.dist-info/WHEEL
ekf_slam-0.0.2.dist-info/METADATA
ekf_slam-0.0.2.dist-info/RECORD
